nats/client/__init__.py
nats/client/connection.py
nats/client/errors.py
nats/client/message.py
nats/client/subscription.py
nats/client/protocol/__init__.py
nats/client/protocol/command.py
nats/client/protocol/message.py
nats/client/protocol/types.py
nats_core-0.1.0.dist-info/METADATA
nats_core-0.1.0.dist-info/WHEEL
nats_core-0.1.0.dist-info/top_level.txt
nats_core-0.1.0.dist-info/RECORD
