Metadata-Version: 2.4
Name: nats-core
Version: 0.1.0
Summary: NATS core implementation in Python
Author-email: Casper Beyer <casper@synadia.com>
License-Expression: MIT
Project-URL: Documentation, https://github.com/nats-io/nats.py
Project-URL: Issues, https://github.com/nats-io/nats.py/issues
Project-URL: Source, https://github.com/nats-io/nats.py
Keywords: nats,messaging,client
Classifier: Development Status :: 4 - Beta
Classifier: Programming Language :: Python
Classifier: Programming Language :: Python :: 3.13
Classifier: Programming Language :: Python :: Implementation :: CPython
Classifier: Programming Language :: Python :: Implementation :: PyPy
Requires-Python: >=3.13
Provides-Extra: nkeys
Requires-Dist: nkeys>=0.1.0; extra == "nkeys"
